__init__.py
distributed_lru_cache/__init__.py
distributed_lru_cache/cache.py
distributed_lru_cache/utils.py
distributed_lru_cache-0.0.2.dist-info/DESCRIPTION.rst
distributed_lru_cache-0.0.2.dist-info/METADATA
distributed_lru_cache-0.0.2.dist-info/RECORD
distributed_lru_cache-0.0.2.dist-info/WHEEL
distributed_lru_cache-0.0.2.dist-info/entry_points.txt
distributed_lru_cache-0.0.2.dist-info/metadata.json
distributed_lru_cache-0.0.2.dist-info/top_level.txt
